{
	"name": "AzureSqlTable4",
	"properties": {
		"linkedServiceName": {
			"referenceName": "AzureSqlDatabase1",
			"type": "LinkedServiceReference"
		},
		"annotations": [],
		"type": "AzureSqlTable",
		"schema": [
			{
				"name": "customer_id",
				"type": "varchar"
			},
			{
				"name": "phone",
				"type": "varchar"
			},
			{
				"name": "countrycode",
				"type": "varchar"
			},
			{
				"name": "country",
				"type": "varchar"
			},
			{
				"name": "state",
				"type": "varchar"
			}
		],
		"typeProperties": {
			"schema": "dbo",
			"table": "Customer0"
		}
	},
	"type": "Microsoft.DataFactory/factories/datasets"
}